[
  {
    "name": "بندكت كرواسون",
    "category": "Breakfast",
    "selling_price": 34.0,
    "sales_count": 698,
    "direct_cost": 6.5,
    "total_cost": 8.0,
    "app_fee": 1.5,
    "profit_margin": 26.0,
    "annual_profit": 18148.0,
    "profit_margin_pct": 76.5,
    "revenue": 23732,
    "monthly_profit": null
  },
  {
    "name": "سبايسي تونة",
    "category": "Breakfast",
    "selling_price": 29.0,
    "sales_count": 1295,
    "direct_cost": 7.9,
    "total_cost": 9.71,
    "app_fee": 1.81,
    "profit_margin": 19.29,
    "annual_profit": 24980.55,
    "profit_margin_pct": 66.5,
    "revenue": 37555,
    "monthly_profit": null
  },
  {
    "name": "حلومي بيستو",
    "category": "Breakfast",
    "selling_price": 27.0,
    "sales_count": 3246,
    "direct_cost": 7.2,
    "total_cost": 8.85,
    "app_fee": 1.65,
    "profit_margin": 18.15,
    "annual_profit": 58914.9,
    "profit_margin_pct": 67.2,
    "revenue": 87642,
    "monthly_profit": null
  },
  {
    "name": "أيق بريوش",
    "category": "Breakfast",
    "selling_price": 26.0,
    "sales_count": 2049,
    "direct_cost": 7.45,
    "total_cost": 9.16,
    "app_fee": 1.71,
    "profit_margin": 16.84,
    "annual_profit": 34505.16,
    "profit_margin_pct": 64.8,
    "revenue": 53274,
    "monthly_profit": null
  },
  {
    "name": "كرواسون تركي",
    "category": "Breakfast",
    "selling_price": 28.0,
    "sales_count": 925,
    "direct_cost": 4.9,
    "total_cost": 6.02,
    "app_fee": 1.12,
    "profit_margin": 21.98,
    "annual_profit": 20331.5,
    "profit_margin_pct": 78.5,
    "revenue": 25900,
    "monthly_profit": null
  },
  {
    "name": "ثلاثة أجبان",
    "category": "Breakfast",
    "selling_price": 27.0,
    "sales_count": 715,
    "direct_cost": 5.74,
    "total_cost": 7.06,
    "app_fee": 1.32,
    "profit_margin": 19.94,
    "annual_profit": 14257.1,
    "profit_margin_pct": 73.9,
    "revenue": 19305,
    "monthly_profit": null
  },
  {
    "name": "بيض الأفوكادو",
    "category": "Breakfast",
    "selling_price": 28.0,
    "sales_count": 1075,
    "direct_cost": 8.85,
    "total_cost": 10.85,
    "app_fee": 2.0,
    "profit_margin": 17.15,
    "annual_profit": 18436.25,
    "profit_margin_pct": 61.2,
    "revenue": 30100,
    "monthly_profit": null
  },
  {
    "name": "كابتشينو",
    "category": "Beverages",
    "selling_price": 17.0,
    "sales_count": 7046,
    "direct_cost": 3.0,
    "total_cost": 3.69,
    "app_fee": 0.69,
    "profit_margin": 13.31,
    "annual_profit": 93782.26,
    "monthly_profit": 7815.18,
    "profit_margin_pct": 78.3,
    "revenue": 119782
  },
  {
    "name": "لاتية",
    "category": "Beverages",
    "selling_price": 17.0,
    "sales_count": 8854,
    "direct_cost": 3.0,
    "total_cost": 3.69,
    "app_fee": 0.69,
    "profit_margin": 13.31,
    "annual_profit": 117846.74,
    "monthly_profit": 9820.56,
    "profit_margin_pct": 78.3,
    "revenue": 150518
  },
  {
    "name": "فلات وايت",
    "category": "Beverages",
    "selling_price": 17.0,
    "sales_count": 10107,
    "direct_cost": 2.9,
    "total_cost": 3.55,
    "app_fee": 0.65,
    "profit_margin": 13.45,
    "annual_profit": 135939.15,
    "monthly_profit": 11328.26,
    "profit_margin_pct": 79.1,
    "revenue": 171819
  },
  {
    "name": "امريكانو",
    "category": "Beverages",
    "selling_price": 15.0,
    "sales_count": 2939,
    "direct_cost": 1.7,
    "total_cost": 2.09,
    "app_fee": 0.39,
    "profit_margin": 12.91,
    "annual_profit": 37939.55,
    "monthly_profit": 3161.62,
    "profit_margin_pct": 86.1,
    "revenue": 44085
  },
  {
    "name": "بلاك كوفي",
    "category": "Beverages",
    "selling_price": 14.0,
    "sales_count": 110349,
    "direct_cost": 1.6,
    "total_cost": 1.96,
    "app_fee": 0.36,
    "profit_margin": 12.04,
    "annual_profit": 1328601.96,
    "monthly_profit": 110716.83,
    "profit_margin_pct": 86.0,
    "revenue": 1544886
  },
  {
    "name": "ايس امريكانو",
    "category": "Beverages",
    "selling_price": 16.0,
    "sales_count": 2676,
    "direct_cost": 1.7,
    "total_cost": 3.55,
    "app_fee": 0.65,
    "profit_margin": 12.45,
    "annual_profit": 33316.2,
    "monthly_profit": 2776.35,
    "profit_margin_pct": 77.8,
    "revenue": 42816
  },
  {
    "name": "ايس لاتية",
    "category": "Beverages",
    "selling_price": 18.0,
    "sales_count": 2547,
    "direct_cost": 3.0,
    "total_cost": 3.69,
    "app_fee": 0.69,
    "profit_margin": 14.31,
    "annual_profit": 36447.57,
    "monthly_profit": 3037.29,
    "profit_margin_pct": 79.5,
    "revenue": 45846
  },
  {
    "name": "ايس فلات وايت",
    "category": "Beverages",
    "selling_price": 17.0,
    "sales_count": 730,
    "direct_cost": 2.9,
    "total_cost": 3.55,
    "app_fee": 0.65,
    "profit_margin": 13.45,
    "annual_profit": 9818.5,
    "monthly_profit": 818.2,
    "profit_margin_pct": 79.1,
    "revenue": 12410
  },
  {
    "name": "ايس سبانش لاتية",
    "category": "Beverages",
    "selling_price": 22.0,
    "sales_count": 16971,
    "direct_cost": 3.75,
    "total_cost": 4.61,
    "app_fee": 0.86,
    "profit_margin": 17.39,
    "annual_profit": 295125.69,
    "monthly_profit": 24593.8,
    "profit_margin_pct": 79.0,
    "revenue": 373362
  },
  {
    "name": "سبانش لاتية",
    "category": "Beverages",
    "selling_price": 19.0,
    "sales_count": 10041,
    "direct_cost": 3.82,
    "total_cost": 4.69,
    "app_fee": 0.87,
    "profit_margin": 14.31,
    "annual_profit": 141879.33,
    "monthly_profit": 11823.27,
    "profit_margin_pct": 75.3,
    "revenue": 190779
  },
  {
    "name": "v60 hot",
    "category": "Beverages",
    "selling_price": 19.0,
    "sales_count": 16113,
    "direct_cost": 1.78,
    "total_cost": 2.18,
    "app_fee": 0.4,
    "profit_margin": 16.82,
    "annual_profit": 271020.66,
    "monthly_profit": 22585.0,
    "profit_margin_pct": 88.5,
    "revenue": 306147
  },
  {
    "name": "كيمكس",
    "category": "Beverages",
    "selling_price": 19.0,
    "sales_count": 237,
    "direct_cost": 1.78,
    "total_cost": 2.18,
    "app_fee": 0.4,
    "profit_margin": 16.82,
    "annual_profit": 3879.69,
    "monthly_profit": 323.3,
    "profit_margin_pct": 88.5,
    "revenue": 4503
  },
  {
    "name": "ice v60",
    "category": "Beverages",
    "selling_price": 19.0,
    "sales_count": 66603,
    "direct_cost": 2.13,
    "total_cost": 2.63,
    "app_fee": 0.5,
    "profit_margin": 16.37,
    "annual_profit": 1090291.11,
    "monthly_profit": 90857.59,
    "profit_margin_pct": 86.2,
    "revenue": 1265457
  },
  {
    "name": "ايس كيمكس",
    "category": "Beverages",
    "selling_price": 19.0,
    "sales_count": 603,
    "direct_cost": 2.13,
    "total_cost": 2.63,
    "app_fee": 0.5,
    "profit_margin": 16.37,
    "annual_profit": 9871.11,
    "monthly_profit": 822.59,
    "profit_margin_pct": 86.2,
    "revenue": 11457
  },
  {
    "name": "مياة",
    "category": "Beverages",
    "selling_price": 4.0,
    "sales_count": 36250,
    "direct_cost": 1.55,
    "total_cost": 1.9,
    "app_fee": 0.35,
    "profit_margin": 2.1,
    "annual_profit": 76125.0,
    "monthly_profit": 6343.75,
    "profit_margin_pct": 52.5,
    "revenue": 145000
  },
  {
    "name": "اسبرسو",
    "category": "Beverages",
    "selling_price": 9.0,
    "sales_count": 2920,
    "direct_cost": 1.7,
    "total_cost": 2.08,
    "app_fee": 0.38,
    "profit_margin": 6.92,
    "annual_profit": 20206.4,
    "monthly_profit": 1683.86,
    "profit_margin_pct": 76.9,
    "revenue": 26280
  },
  {
    "name": "كرتادو",
    "category": "Beverages",
    "selling_price": 14.0,
    "sales_count": 1352,
    "direct_cost": 2.36,
    "total_cost": 2.9,
    "app_fee": 0.54,
    "profit_margin": 11.1,
    "annual_profit": 15007.2,
    "monthly_profit": 1250.6,
    "profit_margin_pct": 79.3,
    "revenue": 18928
  },
  {
    "name": "اولاس موهيتو",
    "category": "Beverages",
    "selling_price": 20.0,
    "sales_count": 3171,
    "direct_cost": 5.3,
    "total_cost": 6.51,
    "app_fee": 1.21,
    "profit_margin": 13.49,
    "annual_profit": 42776.79,
    "monthly_profit": 3564.73,
    "profit_margin_pct": 67.5,
    "revenue": 63420
  },
  {
    "name": "سول موهيتو",
    "category": "Beverages",
    "selling_price": 20.0,
    "sales_count": 3860,
    "direct_cost": 5.3,
    "total_cost": 6.51,
    "app_fee": 1.21,
    "profit_margin": 13.49,
    "annual_profit": 52071.4,
    "monthly_profit": 4339.28,
    "profit_margin_pct": 67.5,
    "revenue": 77200
  },
  {
    "name": "ايس تي",
    "category": "Beverages",
    "selling_price": 22.0,
    "sales_count": 12315,
    "direct_cost": 3.5,
    "total_cost": 4.3,
    "app_fee": 0.8,
    "profit_margin": 17.7,
    "annual_profit": 217975.5,
    "monthly_profit": 18164.62,
    "profit_margin_pct": 80.5,
    "revenue": 270930
  },
  {
    "name": "ايس ماتشا",
    "category": "Beverages",
    "selling_price": 25.0,
    "sales_count": 4881,
    "direct_cost": 7.2,
    "total_cost": 8.85,
    "app_fee": 1.65,
    "profit_margin": 16.15,
    "annual_profit": 78828.15,
    "monthly_profit": 6569.0,
    "profit_margin_pct": 64.6,
    "revenue": 122025
  },
  {
    "name": "ترمس قهوة",
    "category": "Beverages",
    "selling_price": 45.0,
    "sales_count": 297,
    "direct_cost": 13.52,
    "total_cost": 16.63,
    "app_fee": 3.11,
    "profit_margin": 28.37,
    "annual_profit": 8425.89,
    "monthly_profit": 702.15,
    "profit_margin_pct": 63.0,
    "revenue": 13365
  },
  {
    "name": "هوت شوكليت",
    "category": "Beverages",
    "selling_price": 22.0,
    "sales_count": 15834,
    "direct_cost": 6.3,
    "total_cost": 7.74,
    "app_fee": 1.44,
    "profit_margin": 14.26,
    "annual_profit": 225792.84,
    "monthly_profit": 18816.0,
    "profit_margin_pct": 64.8,
    "revenue": 348348
  },
  {
    "name": "بينكي ماتشا",
    "category": "Beverages",
    "selling_price": 26.0,
    "sales_count": 333,
    "direct_cost": 3.5,
    "total_cost": 4.3,
    "app_fee": 0.8,
    "profit_margin": 21.7,
    "annual_profit": 7226.1,
    "monthly_profit": 602.17,
    "profit_margin_pct": 83.5,
    "revenue": 8658
  },
  {
    "name": "تراميسو لاتية",
    "category": "Beverages",
    "selling_price": 26.0,
    "sales_count": 1593,
    "direct_cost": 4.75,
    "total_cost": 5.84,
    "app_fee": 1.09,
    "profit_margin": 20.16,
    "annual_profit": 32114.88,
    "monthly_profit": 2676.24,
    "profit_margin_pct": 77.5,
    "revenue": 41418
  },
  {
    "name": "سعودي لاتية",
    "category": "Beverages",
    "selling_price": 25.0,
    "sales_count": 562,
    "direct_cost": 4.0,
    "total_cost": 4.92,
    "app_fee": 0.92,
    "profit_margin": 20.08,
    "annual_profit": 11284.96,
    "monthly_profit": 940.41,
    "profit_margin_pct": 80.3,
    "revenue": 14050
  },
  {
    "name": "ام علي",
    "category": "Desserts",
    "selling_price": 26.0,
    "sales_count": 5312,
    "direct_cost": 3.5,
    "total_cost": 4.3,
    "app_fee": 0.8,
    "profit_margin": 21.7,
    "annual_profit": 115270.4,
    "monthly_profit": 9605.86,
    "profit_margin_pct": 83.5,
    "revenue": 138112
  },
  {
    "name": "كيك جوز هند",
    "category": "Desserts",
    "selling_price": 18.0,
    "sales_count": 4259,
    "direct_cost": 2.3,
    "total_cost": 2.82,
    "app_fee": 0.52,
    "profit_margin": 15.18,
    "annual_profit": 64651.62,
    "monthly_profit": 5387.63,
    "profit_margin_pct": 84.3,
    "revenue": 76662
  },
  {
    "name": "ميلفية برولية",
    "category": "Desserts",
    "selling_price": 33.0,
    "sales_count": 7123,
    "direct_cost": 3.75,
    "total_cost": 4.61,
    "app_fee": 0.86,
    "profit_margin": 28.39,
    "annual_profit": 202221.97,
    "monthly_profit": 16851.83,
    "profit_margin_pct": 86.0,
    "revenue": 235059
  },
  {
    "name": "سان سباستيان",
    "category": "Desserts",
    "selling_price": 29.0,
    "sales_count": 6400,
    "direct_cost": 3.98,
    "total_cost": 4.89,
    "app_fee": 0.91,
    "profit_margin": 24.11,
    "annual_profit": 154304.0,
    "monthly_profit": 12858.66,
    "profit_margin_pct": 83.1,
    "revenue": 185600
  },
  {
    "name": "فرنش توست",
    "category": "Desserts",
    "selling_price": 21.0,
    "sales_count": 32529,
    "direct_cost": 1.75,
    "total_cost": 2.15,
    "app_fee": 0.4,
    "profit_margin": 18.85,
    "annual_profit": 613171.65,
    "monthly_profit": 51097.63,
    "profit_margin_pct": 89.8,
    "revenue": 683109
  },
  {
    "name": "تراميسو",
    "category": "Desserts",
    "selling_price": 25.0,
    "sales_count": 9217,
    "direct_cost": 3.8,
    "total_cost": 4.67,
    "app_fee": 0.87,
    "profit_margin": 20.33,
    "annual_profit": 187381.61,
    "monthly_profit": 15615.13,
    "profit_margin_pct": 81.3,
    "revenue": 230425
  },
  {
    "name": "وافل ستيك",
    "category": "Desserts",
    "selling_price": 22.0,
    "sales_count": 37990,
    "direct_cost": 2.9,
    "total_cost": 3.56,
    "app_fee": 0.66,
    "profit_margin": 18.44,
    "annual_profit": 700535.6,
    "monthly_profit": 58377.96,
    "profit_margin_pct": 83.8,
    "revenue": 835780
  },
  {
    "name": "ماربل كيك",
    "category": "Desserts",
    "selling_price": 12.0,
    "sales_count": 3240,
    "direct_cost": 1.1,
    "total_cost": 1.35,
    "app_fee": 0.25,
    "profit_margin": 10.65,
    "annual_profit": 34506.0,
    "monthly_profit": 2875.5,
    "profit_margin_pct": 88.8,
    "revenue": 38880
  },
  {
    "name": "براونيز",
    "category": "Desserts",
    "selling_price": 12.0,
    "sales_count": 5556,
    "direct_cost": 1.4,
    "total_cost": 1.72,
    "app_fee": 0.32,
    "profit_margin": 10.28,
    "annual_profit": 57115.68,
    "monthly_profit": 4759.64,
    "profit_margin_pct": 85.7,
    "revenue": 66672
  },
  {
    "name": "لافا لوتيس",
    "category": "Desserts",
    "selling_price": 22.0,
    "sales_count": 0,
    "direct_cost": 5.6,
    "total_cost": 6.88,
    "app_fee": 1.28,
    "profit_margin": 15.12,
    "annual_profit": 0.0,
    "monthly_profit": 0.0,
    "profit_margin_pct": 68.7,
    "revenue": 0
  },
  {
    "name": "ماتلدا سولا",
    "category": "Desserts",
    "selling_price": 28.0,
    "sales_count": 2481,
    "direct_cost": 2.39,
    "total_cost": 2.93,
    "app_fee": 0.54,
    "profit_margin": 25.07,
    "annual_profit": 62198.67,
    "monthly_profit": 5183.22,
    "profit_margin_pct": 89.5,
    "revenue": 69468
  },
  {
    "name": "كوكيز نوتيلا",
    "category": "Desserts",
    "selling_price": 21.0,
    "sales_count": 577,
    "direct_cost": 2.95,
    "total_cost": 3.62,
    "app_fee": 0.67,
    "profit_margin": 17.38,
    "annual_profit": 10028.26,
    "monthly_profit": 835.68,
    "profit_margin_pct": 82.8,
    "revenue": 12117
  },
  {
    "name": "شوكليت بودينق",
    "category": "Desserts",
    "selling_price": 29.0,
    "sales_count": 76,
    "direct_cost": 2.95,
    "total_cost": 3.62,
    "app_fee": 0.67,
    "profit_margin": 25.38,
    "annual_profit": 1928.88,
    "monthly_profit": 160.74,
    "profit_margin_pct": 87.5,
    "revenue": 2204
  }
]